nurbspy/__init__.py
nurbspy/graphics.py
nurbspy/jax/__init__.py
nurbspy/jax/nurbs_basis_functions.py
nurbspy/jax/nurbs_curve.py
nurbspy/jax/nurbs_curve_circular_arc.py
nurbspy/nurbs_basis_functions.py
nurbspy/nurbs_curve.py
nurbspy/nurbs_curve_circular_arc.py
nurbspy/nurbs_surface.py
nurbspy/nurbs_surface_bilinear.py
nurbspy/nurbs_surface_coons.py
nurbspy/nurbs_surface_extruded.py
nurbspy/nurbs_surface_revolution.py
nurbspy/nurbs_surface_ruled.py
nurbspy-1.2.4.dist-info/LICENSE.md
nurbspy-1.2.4.dist-info/METADATA
nurbspy-1.2.4.dist-info/WHEEL
nurbspy-1.2.4.dist-info/RECORD
