Metadata-Version: 2.1
Name: nurbspy
Version: 1.2.4
Summary: A lightweight library for NURBS curves and surfaces
Home-page: https://github.com/turbo-sim/nurbspy
License: MIT
Author: Roberto Agromayor
Author-email: rober.agro@gmail.com
Requires-Python: >=3.11,<3.14
Classifier: License :: OSI Approved :: MIT License
Classifier: Programming Language :: Python :: 3
Classifier: Programming Language :: Python :: 3.11
Classifier: Programming Language :: Python :: 3.12
Requires-Dist: PyYAML (>=6.0.2,<7.0.0)
Requires-Dist: cycler (>=0.12.1,<0.13.0)
Requires-Dist: diffrax (>=0.7.0,<0.8.0)
Requires-Dist: equinox (>=0.12.0,<0.13.0)
Requires-Dist: jax (>=0.6.0,<0.7.0)
Requires-Dist: jaxlib (>=0.6.0,<0.7.0)
Requires-Dist: matplotlib (>=3.10.6,<4.0.0)
Requires-Dist: numba (>=0.62.0,<0.63.0)
Requires-Dist: numpy (>=2.3.0,<3.0.0)
Requires-Dist: optimistix (>=0.0.10,<0.0.11)
Requires-Dist: quadax (>=0.2.10,<0.3.0)
Requires-Dist: scipy (>=1.16.1,<2.0.0)
Requires-Dist: toml (>=0.10.2,<0.11.0)
Project-URL: Documentation, https://github.com/turbo-sim/nurbspy
Project-URL: Repository, https://github.com/turbo-sim/nurbspy
